filecache.py
setup.py
yelp.py
python_yelp_v2.egg-info/PKG-INFO
python_yelp_v2.egg-info/SOURCES.txt
python_yelp_v2.egg-info/dependency_links.txt
python_yelp_v2.egg-info/requires.txt
python_yelp_v2.egg-info/top_level.txt
test/test_client.py