Metadata-Version: 1.0
Name: python-yelp-v2
Version: 0.5.7
Summary: A Python wrapper around the Yelp API v2
Home-page: https://github.com/mathisonian/python-yelp-v2
Author: Matthew Conlen
Author-email: github@mathisonian.com
License: MIT
Keywords: yelp api
Platform: UNKNOWN
